serialiJSON/__init__.py
serialiJSON/serialiJSON.py
serialiJSON-0.0.2.dist-info/LICENSE
serialiJSON-0.0.2.dist-info/METADATA
serialiJSON-0.0.2.dist-info/WHEEL
serialiJSON-0.0.2.dist-info/top_level.txt
serialiJSON-0.0.2.dist-info/RECORD
