Metadata-Version: 2.1
Name: serialiJSON
Version: 0.0.2
Summary: A simple converter from complex objects to JSON
Home-page: https://github.com/matias-alejandro/serialiJSON
Author: Matías Del Pin
Author-email: madelpin@protonmail.com
License: UNKNOWN
Project-URL: Source, https://github.com/matias-alejandro/serialiJSON
Project-URL: Tracker, https://github.com/matias-alejandro/serialiJSON/issues
Platform: UNKNOWN
Classifier: Programming Language :: Python
Classifier: License :: OSI Approved :: MIT License
Classifier: Operating System :: OS Independent
Classifier: Topic :: Software Development :: Libraries :: Python Modules
Requires-Python: >=2.7
License-File: LICENSE
